cloneme
