Metadata-Version: 1.2
Name: cloneme
Version: 0.1.2
Summary: A git clone wrapper to make cloning repos easier
Home-page: http://github.com/LucianoFromTrelew/cloneme
Author: Luciano Serruya Aloisi
Author-email: lucianoserruya@gmail.com
License: MIT
Keywords: git clone wrapper
Platform: UNKNOWN
Requires-Python: >=3
